indexical_sdk/__init__.py
indexical_sdk-0.0.1.dist-info/METADATA
indexical_sdk-0.0.1.dist-info/WHEEL
indexical_sdk-0.0.1.dist-info/licenses/LICENSE
indexical_sdk-0.0.1.dist-info/RECORD
