Metadata-Version: 2.1
Name: indexical_sdk
Version: 0.0.1
Summary: Indexical SDK (for Python)
Project-URL: Homepage, https://github.com/indexical/indexical-sdk-py
Project-URL: Issues, https://github.com/indexical/indexical-sdk-py/issues
Author-email: Vishnu Menon <me@vishnumenon.com>
License-File: LICENSE
Classifier: License :: OSI Approved :: MIT License
Classifier: Operating System :: OS Independent
Classifier: Programming Language :: Python :: 3
Requires-Python: >=3.2
Requires-Dist: packaging
